astreintes-1.1.0.dist-info/METADATA
astreintes-1.1.0.dist-info/WHEEL
astreintes-1.1.0.dist-info/entry_points.txt
astreintes/__init__.py
astreintes/calculs.py
astreintes/models.py
astreintes/sheets.py
tests/.pytest_cache/.gitignore
tests/.pytest_cache/CACHEDIR.TAG
tests/.pytest_cache/README.md
tests/.pytest_cache/v/cache/lastfailed
tests/.pytest_cache/v/cache/nodeids
tests/.pytest_cache/v/cache/stepwise
tests/__init__.py
tests/test_astreintes.py
tests/test_integration.py
tests/test_models.py
astreintes-1.1.0.dist-info/RECORD
