Metadata-Version: 2.1
Name: astreintes
Version: 1.1.0
Summary: Default template for PDM package
Author-Email: Olivier Winter <olivier.winter@hotmail.fr>
License: MIT
Requires-Python: >=3.10
Requires-Dist: gspread
Requires-Dist: ipython
Requires-Dist: numpy
Requires-Dist: pandas
Requires-Dist: pandera
Requires-Dist: pydantic
Requires-Dist: scipy
